djx/__init__.py
djx/database.py
djx/environment.py
djx/functional.py
djx/static.py
djx/urls.py
djx-0.0.6.dist-info/LICENSE
djx-0.0.6.dist-info/LICENSE.md
djx-0.0.6.dist-info/WHEEL
djx-0.0.6.dist-info/METADATA
djx-0.0.6.dist-info/RECORD
