Metadata-Version: 2.1
Name: djx
Version: 0.0.6
Summary: Common utilities and dependencies for the modern Django project
License: MIT
Author: aleontiev
Author-email: alonetiev@gmail.com
Requires-Python: >=3
Classifier: License :: OSI Approved :: MIT License
Classifier: Programming Language :: Python :: 3
Classifier: Programming Language :: Python :: 3.4
Classifier: Programming Language :: Python :: 3.5
Classifier: Programming Language :: Python :: 3.6
Classifier: Programming Language :: Python :: 3.7
Classifier: Programming Language :: Python :: 3.8
Requires-Dist: dj-database-url
Requires-Dist: dj-static
Requires-Dist: django
Requires-Dist: gunicorn
